log_soso/__init__.py
log_soso/test.py
log_soso-1.0.3.dist-info/LICENSE
log_soso-1.0.3.dist-info/WHEEL
log_soso-1.0.3.dist-info/METADATA
log_soso-1.0.3.dist-info/RECORD
