Metadata-Version: 2.1
Name: log_soso
Version: 1.0.3
Summary: Some logging enhancements, such as log error with traceback, redirect STDOUT,
Author-email: Leon Dionne <ldionne@dridesign.sh.cn>
Classifier: License :: OSI Approved :: GNU General Public License v3 or later (GPLv3+)
Project-URL: Home, https://github.com/Zen-Master-SoSo/log_soso
